cleany_cli/__init__.py
cleany_cli/__main__.py
cleany_cli/cleany.py
cleany_cli-0.2.0.dist-info/licenses/LICENSE
cleany_cli-0.2.0.dist-info/METADATA
cleany_cli-0.2.0.dist-info/WHEEL
cleany_cli-0.2.0.dist-info/entry_points.txt
cleany_cli-0.2.0.dist-info/top_level.txt
cleany_cli-0.2.0.dist-info/RECORD
