Metadata-Version: 2.4
Name: cleany-cli
Version: 0.2.0
Summary: Interactive CLI tool to clean and prune tabular data files
Author-email: espehon <espehon@gmail.com>
License: MIT
Project-URL: Homepage, https://github.com/espehon/cleany-cli
Project-URL: Repository, https://github.com/espehon/cleany-cli
Project-URL: Issues, https://github.com/espehon/cleany-cli/issues
Classifier: Development Status :: 3 - Alpha
Classifier: Environment :: Console
Classifier: Intended Audience :: Developers
Classifier: Intended Audience :: End Users/Desktop
Classifier: License :: OSI Approved :: MIT License
Classifier: Natural Language :: English
Classifier: Operating System :: OS Independent
Classifier: Programming Language :: Python
Classifier: Programming Language :: Python :: 3
Classifier: Programming Language :: Python :: 3.8
Classifier: Programming Language :: Python :: 3.9
Classifier: Programming Language :: Python :: 3.10
Classifier: Programming Language :: Python :: 3.11
Classifier: Programming Language :: Python :: 3.12
Classifier: Topic :: Office/Business
Classifier: Topic :: Utilities
Requires-Python: >=3.8
License-File: LICENSE
Requires-Dist: pandas>=2.0
Requires-Dist: questionary>=2.0
Requires-Dist: openpyxl>=3.0
Requires-Dist: pyarrow>=14.0
Requires-Dist: halo>=0.0.31
Dynamic: license-file
